cms/__init__.py
cms/__init__.pyc
cms/admin.py
cms/admin.pyc
cms/apps.py
cms/context_processors.py
cms/context_processors.pyc
cms/models.py
cms/models.pyc
cms/sitemaps.py
cms/tests.py
cms/urls.py
cms/urls.pyc
cms/views.py
cms/views.pyc
cms/__pycache__/__init__.cpython-36.pyc
cms/__pycache__/admin.cpython-36.pyc
cms/__pycache__/apps.cpython-36.pyc
cms/__pycache__/context_processors.cpython-36.pyc
cms/__pycache__/models.cpython-36.pyc
cms/__pycache__/sitemaps.cpython-36.pyc
cms/__pycache__/urls.cpython-36.pyc
cms/__pycache__/views.cpython-36.pyc
cms/migrations/0001_initial.py
cms/migrations/__init__.py
cms/migrations/__init__.pyc
cms/migrations/__pycache__/0001_initial.cpython-36.pyc
cms/migrations/__pycache__/__init__.cpython-36.pyc
cms/templates/cms/base.html
cms/templates/cms/blog_index.html
cms/templates/cms/page.html
cms/templates/cms/includes/blog_header.html
cms/templates/cms/includes/blog_index_content.html
cms/templates/cms/includes/blog_index_entry.html
cms/templates/cms/includes/byline.html
cms/templates/cms/includes/featured_post.html
django_simple_cms-0.1.2.dist-info/LICENSE
django_simple_cms-0.1.2.dist-info/METADATA
django_simple_cms-0.1.2.dist-info/WHEEL
django_simple_cms-0.1.2.dist-info/top_level.txt
django_simple_cms-0.1.2.dist-info/RECORD
