Metadata-Version: 2.1
Name: django-simple-cms
Version: 0.1.2
Summary: A simple  CMS for django
Home-page: https://github.com/vinaypai/django-simple-cms/
Author: Vinay Pai
Author-email: vinay@vinaypai.com
License: UNKNOWN
Platform: UNKNOWN
Classifier: Development Status :: 3 - Alpha
Classifier: Environment :: Web Environment
Classifier: Framework :: Django
Classifier: Intended Audience :: Developers
Classifier: License :: OSI Approved :: MIT License
Classifier: Operating System :: OS Independent
Classifier: Programming Language :: Python :: 3
Classifier: Programming Language :: Python :: 2.7
Classifier: Topic :: Internet :: WWW/HTTP :: Dynamic Content :: Content Management System
Requires-Dist: django-mptt (>=0.9)
Requires-Dist: django (>=1.11)
Requires-Dist: pillow (>=2.1)
